FHIL_spatial_utils/__init__.py
FHIL_spatial_utils/plotting.py
FHIL_spatial_utils/svm.py
fhil_spatial_utils-0.1.1.dist-info/METADATA
fhil_spatial_utils-0.1.1.dist-info/WHEEL
fhil_spatial_utils-0.1.1.dist-info/licenses/LICENSE
fhil_spatial_utils-0.1.1.dist-info/RECORD
