Metadata-Version: 2.4
Name: FHIL_spatial_utils
Version: 0.1.1
Summary: Utility functions for spatial RNA analysis
Project-URL: Homepage, https://github.com/Fred-Hutch-Innovation-Lab/spatial_utils
Project-URL: Issues, https://github.com/Fred-Hutch-Innovation-Lab/spatial_utils/issues
Author-email: Derrik Gratz <derrik.gratz@gmail.com>
License-File: LICENSE
Requires-Python: >=3.9
Requires-Dist: anndata
Requires-Dist: matplotlib
Requires-Dist: numpy
Requires-Dist: pandas
Requires-Dist: pybiomart
Requires-Dist: scanpy
Requires-Dist: seaborn
